isbnlib_oclc/__init__.py
isbnlib_oclc/_oclc.py
isbnlib_oclc-0.0.1.post1.dist-info/LICENSE-LGPL.txt
isbnlib_oclc-0.0.1.post1.dist-info/METADATA
isbnlib_oclc-0.0.1.post1.dist-info/WHEEL
isbnlib_oclc-0.0.1.post1.dist-info/entry_points.txt
isbnlib_oclc-0.0.1.post1.dist-info/top_level.txt
isbnlib_oclc-0.0.1.post1.dist-info/RECORD
