Metadata-Version: 2.1
Name: isbnlib-oclc
Version: 0.0.1.post1
Summary: DISCONTINUED! A plugin for isbnlib that pulls metadata from classify.oclc.org.
Home-page: https://github.com/xlcnd/isbnlib-oclc
Author: xlcnd
Author-email: xlcnd@outlook.com
License: LGPL v3
Download-URL: https://github.com/xlcnd/isbnlib-oclc/archive/v0.0.2.zip
Keywords: ISBN isbnlib oclc bibliographic-references
Platform: UNKNOWN
Classifier: Programming Language :: Python
Classifier: Programming Language :: Python :: 2
Classifier: Programming Language :: Python :: 2.7
Classifier: Programming Language :: Python :: 3
Classifier: Programming Language :: Python :: 3.5
Classifier: Programming Language :: Python :: 3.6
Classifier: Programming Language :: Python :: 3.7
Classifier: License :: OSI Approved :: GNU Lesser General Public License v3 (LGPLv3)
Classifier: Operating System :: OS Independent
Classifier: Development Status :: 3 - Alpha
Classifier: Intended Audience :: Developers
Classifier: Intended Audience :: End Users/Desktop
Classifier: Environment :: Console
Classifier: Topic :: Text Processing :: General
Classifier: Topic :: Software Development :: Libraries :: Python Modules
Requires-Dist: isbnlib (<3.10.0,>=3.9.1)
